README
setup.py
aliyun_mns_sdk_changed.egg-info/PKG-INFO
aliyun_mns_sdk_changed.egg-info/SOURCES.txt
aliyun_mns_sdk_changed.egg-info/dependency_links.txt
aliyun_mns_sdk_changed.egg-info/requires.txt
aliyun_mns_sdk_changed.egg-info/top_level.txt
bin/mnscmd
mns/__init__.py
mns/account.py
mns/mns_client.py
mns/mns_common.py
mns/mns_exception.py
mns/mns_http.py
mns/mns_request.py
mns/mns_tool.py
mns/mns_xml_handler.py
mns/pkg_info.py
mns/queue.py
mns/subscription.py
mns/topic.py