Metadata-Version: 1.0
Name: aliyun-mns-sdk-changed
Version: 1.1.6
Summary: Aliyun Message Service Library
Home-page: UNKNOWN
Author: Aliyun MNS
Author-email: UNKNOWN
License: MIT
Platform: UNKNOWN
